README.md
setup.py
arnoldc/__init__.py
arnoldc/__main__.py
arnoldc/__version__.py
arnoldc/arnoldc.py
pyarnold.egg-info/PKG-INFO
pyarnold.egg-info/SOURCES.txt
pyarnold.egg-info/dependency_links.txt
pyarnold.egg-info/entry_points.txt
pyarnold.egg-info/top_level.txt
test/__init__.py
test/arnoldc_test.py
test/basic_program_test.py
test/logic_test.py
test/method_test.py
test/operator_test.py