Metadata-Version: 2.1
Name: pyarnold
Version: 1.0.1
Summary: Python implementation of ArnoldC
Home-page: https://github.com/cmccandless/arnoldc
Author: Corey McCandless
Author-email: crm1994@gmail.com
License: UNKNOWN
Platform: UNKNOWN
Classifier: Programming Language :: Python :: 3
Classifier: License :: OSI Approved :: MIT License
Classifier: Operating System :: OS Independent
Requires-Python: >=3.5.2
